[
    {      
      "id": 1,
      "img": "http://localhost:8080/img/ourProjectsImg.4d65a9a4.jpg",
      "m_name": "Дом для двух поколений",
      "decr": "Уютная студия в ЖК Адмирал"
    },
    {      
      "id": 2,
      "img": "http://localhost:8080/img/best_sol_img.daf3f928.jpg",
      "m_name": "Дом для двух поколений 2",
      "decr": "Уютная студия в ЖК Капитан"
    },
    {      
      "id": 3,
      "img": "http://localhost:8080/img/examp_1.46a19c00.jpg",
      "m_name": "Дом для двух поколений 3",
      "decr": "Уютная студия в ЖК Майор"
    },
    {      
      "id": 4,
      "img": "http://localhost:8080/img/examp_2.75564caa.jpg",
      "m_name": "Дом для двух поколений 4",
      "decr": "Уютная студия в ЖК Маршал"
    },
    {      
      "id": 5,
      "img": "http://localhost:8080/img/examp_3.afb97930.jpg",
      "m_name": "Дом для двух поколений 4",
      "decr": "Уютная студия в ЖК Маршал"
    },
    {      
      "id": 6,
      "img": "http://localhost:8080/img/examp_4.6b8ebc52.jpg",
      "m_name": "Дом для двух поколений 4",
      "decr": "Уютная студия в ЖК Маршал"
    },
    {      
      "id": 7,
      "img": "http://localhost:8080/img/examp_5.329d7b01.jpg",
      "m_name": "Дом для двух поколений 4",
      "decr": "Уютная студия в ЖК Маршал"
    },
    {      
      "id": 8,
      "img": "http://localhost:8080/img/examp_6.1149f937.jpg",
      "m_name": "Дом для двух поколений 4",
      "decr": "Уютная студия в ЖК Маршал"
    },
    {      
      "id": 9,
      "img": "http://localhost:8080/img/examp_7.c3d7fc55.jpg",
      "m_name": "Дом для двух поколений 4",
      "decr": "Уютная студия в ЖК Маршал"
    }
]